{
  "_fv": 28,
  "_type": "recipe",
  "definition": {
    "recipeType": "Crafting",
    "xpReward": 0.0,
    "cookingTime": 200,
    "recipeRetstackSize": 1,
    "group": "",
    "recipeShapeless": false,
    "recipeSlots": [
      {
        "value": "CUSTOM:Exolium"
      },
      {
        "value": "Items.IRON_INGOT"
      },
      {
        "value": "CUSTOM:Exolium"
      },
      {
        "value": "Items.FEATHER"
      },
      {
        "value": ""
      },
      {
        "value": "Items.FEATHER"
      },
      {
        "value": "Items.IRON_INGOT"
      },
      {
        "value": ""
      },
      {
        "value": "Items.IRON_INGOT"
      }
    ],
    "recipeReturnStack": {
      "value": "CUSTOM:Aventure_Armor.legs"
    },
    "name": "farm_leggings_recipe",
    "namespace": "mod"
  }
}