{
  "type": "minecraft:crafting_shapeless",
  "ingredients": [
    {
      "item": "osalysmod:antimatiere_ingot"
    },
    {
      "item": "osalysmod:antimatiere_ingot"
    },
    {
      "item": "osalysmod:antimatiere_ingot"
    },
    {
      "item": "osalysmod:antimatiere_ingot"
    },
    {
      "item": "osalysmod:antimatiere_ingot"
    },
    {
      "item": "osalysmod:antimatiere_ingot"
    },
    {
      "item": "osalysmod:antimatiere_ingot"
    },
    {
      "item": "osalysmod:antimatiere_ingot"
    },
    {
      "item": "osalysmod:antimatiere_ingot"
    }
  ],
  "result": {
    "item": "osalysmod:deleted_mod_element",
    "count": 1
  }
}